sonofflan/__init__.py
sonofflan/__main__.py
sonofflan/browser.py
sonofflan/config.py
sonofflan/crypto.py
sonofflan/devices/__init__.py
sonofflan/devices/device.py
sonofflan/devices/plug.py
sonofflan/devices/powerplug.py
sonofflan/devices/strip.py
sonofflan/devices/thermoplug.py
sonofflan/errors.py
sonofflan/utils.py
sonofflan-0.4.0.dist-info/LICENSE
sonofflan-0.4.0.dist-info/METADATA
sonofflan-0.4.0.dist-info/WHEEL
sonofflan-0.4.0.dist-info/RECORD
